adf2dms/__main__.py
adf2dms/checksum.py
adf2dms/enums.py
adf2dms/main.py
adf2dms/rle.py
adf2dms-0.0.1.dist-info/LICENSE.txt
adf2dms-0.0.1.dist-info/METADATA
adf2dms-0.0.1.dist-info/WHEEL
adf2dms-0.0.1.dist-info/entry_points.txt
adf2dms-0.0.1.dist-info/top_level.txt
adf2dms-0.0.1.dist-info/RECORD
