Metadata-Version: 2.1
Name: adf2dms
Version: 0.0.1
Summary: Convert Amiga disk images from ADF to DMS (DiskMasher) format
Home-page: https://github.com/dlitz/adf2dms
Author: Darsey Litzenberger
Author-email: dlitz@dlitz.net
License: UNKNOWN
Project-URL: Bug Tracker, https://github.com/dlitz/adf2dms/issues
Platform: UNKNOWN
Classifier: Development Status :: 2 - Pre-Alpha
Classifier: Environment :: Console
Classifier: License :: OSI Approved :: MIT License
Classifier: Programming Language :: Python :: 3
Classifier: Operating System :: OS Independent
Classifier: Topic :: Utilities
Requires-Python: >=3.9
License-File: LICENSE.txt
Requires-Dist: crccheck
